starlette_csrf/__init__.py
starlette_csrf/middleware.py
starlette_csrf/py.typed
starlette_csrf-1.4.5.dist-info/METADATA
starlette_csrf-1.4.5.dist-info/WHEEL
starlette_csrf-1.4.5.dist-info/licenses/LICENSE
starlette_csrf-1.4.5.dist-info/RECORD
