Metadata-Version: 2.1
Name: starlette-csrf
Version: 1.4.5
Summary: Starlette middleware implementing Double Submit Cookie technique to mitigate CSRF
Project-URL: Documentation, https://github.com/frankie567/starlette-csrf
Project-URL: Source, https://github.com/frankie567/starlette-csrf
Author-email: François Voron <fvoron@gmail.com>
License-File: LICENSE
Classifier: Development Status :: 5 - Production/Stable
Classifier: Framework :: AsyncIO
Classifier: Intended Audience :: Developers
Classifier: License :: OSI Approved :: MIT License
Classifier: Programming Language :: Python :: 3 :: Only
Classifier: Programming Language :: Python :: 3.7
Classifier: Programming Language :: Python :: 3.8
Classifier: Programming Language :: Python :: 3.9
Classifier: Programming Language :: Python :: 3.10
Classifier: Topic :: Internet :: WWW/HTTP :: Session
Requires-Python: >=3.7
Requires-Dist: itsdangerous<3.0.0,>=2.0.1
Requires-Dist: starlette>=0.14.2
